guerrillamail.py
python_guerrillamail-0.2.0.dist-info/DESCRIPTION.rst
python_guerrillamail-0.2.0.dist-info/METADATA
python_guerrillamail-0.2.0.dist-info/RECORD
python_guerrillamail-0.2.0.dist-info/WHEEL
python_guerrillamail-0.2.0.dist-info/entry_points.txt
python_guerrillamail-0.2.0.dist-info/metadata.json
python_guerrillamail-0.2.0.dist-info/top_level.txt
