Metadata-Version: 1.1
Name: python-guerrillamail
Version: 0.2.0
Summary: Client for the Guerrillamail temporary email server
Home-page: https://github.com/ncjones/python-guerrillamail
Author: Nathan Jones
Author-email: UNKNOWN
License: GPL3
Keywords: guerrillamail email client cli
Platform: UNKNOWN
Classifier: Development Status :: 5 - Production/Stable
Classifier: Intended Audience :: Developers
Classifier: Natural Language :: English
Classifier: License :: OSI Approved :: GNU General Public License v3 or later (GPLv3+)
Classifier: Programming Language :: Python
Classifier: Programming Language :: Python :: 2
Classifier: Programming Language :: Python :: 2.7
Classifier: Programming Language :: Python :: 3
Classifier: Programming Language :: Python :: 3.3
Classifier: Programming Language :: Python :: 3.4
Classifier: Programming Language :: Python :: 3.5
